setup.cfg
setup.py
Ulakbus.egg-info/PKG-INFO
Ulakbus.egg-info/SOURCES.txt
Ulakbus.egg-info/dependency_links.txt
Ulakbus.egg-info/requires.txt
Ulakbus.egg-info/top_level.txt
ulakbus/__init__.py
ulakbus/manage.py
ulakbus/settings.py
ulakbus/diagrams/akademik_faaliyet.bpmn
ulakbus/diagrams/akademik_performans_hesapla.bpmn
ulakbus/diagrams/akademik_takvim.bpmn
ulakbus/diagrams/bap_anasayfa.bpmn
ulakbus/diagrams/bap_basvuru_inceleme.bpmn
ulakbus/diagrams/bap_basvuru_karari.bpmn
ulakbus/diagrams/bap_basvuru_listeleme.bpmn
ulakbus/diagrams/bap_butce_fisi.bpmn
ulakbus/diagrams/bap_butce_plani.bpmn
ulakbus/diagrams/bap_duyurular.bpmn
ulakbus/diagrams/bap_duyurulari_goruntule.bpmn
ulakbus/diagrams/bap_ek_butce_talep.bpmn
ulakbus/diagrams/bap_ek_sure_talep.bpmn
ulakbus/diagrams/bap_etkinlik_basvuru.bpmn
ulakbus/diagrams/bap_etkinlik_basvuru_degerlendir.bpmn
ulakbus/diagrams/bap_etkinlik_basvuru_incele.bpmn
ulakbus/diagrams/bap_etkinlik_basvuru_listele.bpmn
ulakbus/diagrams/bap_fasil_aktarim_talep.bpmn
ulakbus/diagrams/bap_firma_basvuru_degerlendirme.bpmn
ulakbus/diagrams/bap_firma_kayit.bpmn
ulakbus/diagrams/bap_firma_teklif.bpmn
ulakbus/diagrams/bap_gundem.bpmn
ulakbus/diagrams/bap_hakemlik_daveti.bpmn
ulakbus/diagrams/bap_iletisim.bpmn
ulakbus/diagrams/bap_is_paketi_hazirlama.bpmn
ulakbus/diagrams/bap_kasa_girisi.bpmn
ulakbus/diagrams/bap_komisyon_uyeleri.bpmn
ulakbus/diagrams/bap_komisyon_uyesi_atama.bpmn
ulakbus/diagrams/bap_komisyon_uyesi_etkinlik_basvuru_degerlendir.bpmn
ulakbus/diagrams/bap_makine_techizat_ara.bpmn
ulakbus/diagrams/bap_ogrbasvuru_goruntule.bpmn
ulakbus/diagrams/bap_ogretim_uyesi_basvuru_listeleme.bpmn
ulakbus/diagrams/bap_ogretim_uyesi_etkinlik_basvuru_listele.bpmn
ulakbus/diagrams/bap_proje_arama.bpmn
ulakbus/diagrams/bap_proje_basvuru.bpmn
ulakbus/diagrams/bap_proje_degerlendirme.bpmn
ulakbus/diagrams/bap_proje_degerlendirmeleri_goruntule.bpmn
ulakbus/diagrams/bap_proje_iptal_talep.bpmn
ulakbus/diagrams/bap_proje_raporu.bpmn
ulakbus/diagrams/bap_proje_turleri.bpmn
ulakbus/diagrams/bap_satin_alma_islemleri.bpmn
ulakbus/diagrams/bap_satin_alma_talep.bpmn
ulakbus/diagrams/bap_sikca_sorulan_sorular.bpmn
