Metadata-Version: 1.1
Name: Ulakbus
Version: 0.9.5
Summary: Ulakbus Butunlesik Universite Sistemi
Home-page: https://github.com/zetaops/ulakbus
Author: Zetaops
Author-email: info@zetaops.io
License: GPL v3
Download-URL: https://github.com/zetaops/ulakbus/archive/master.zip
Keywords: academic erp,universty automation system
Platform: UNKNOWN
